streamfeed/__init__.py
streamfeed/csv_parser.py
streamfeed/detect.py
streamfeed/feed_streamer.py
streamfeed/ftp_handler.py
streamfeed/transform.py
streamfeed/xml_parser.py
streamfeed_parser-0.2.8.dist-info/licenses/LICENSE
streamfeed_parser-0.2.8.dist-info/METADATA
streamfeed_parser-0.2.8.dist-info/WHEEL
streamfeed_parser-0.2.8.dist-info/top_level.txt
streamfeed_parser-0.2.8.dist-info/RECORD
