Metadata-Version: 2.4
Name: streamfeed-parser
Version: 0.2.8
Summary: A lightweight streaming parser for CSV and XML feeds over HTTP/FTP with automatic compression handling.
Author-email: Hans-Christian Bøge Pedersen <hello@devwithhans.com>
License: MIT License
Project-URL: Repository, https://github.com/devwithhans/streamfeed-parser
Project-URL: Developer, https://devwithhans.com
Requires-Python: >=3.7
License-File: LICENSE
Requires-Dist: requests>=2.25.0
Dynamic: license-file
